pypesto/C.py
pypesto/__init__.py
pypesto/logging.py
pypesto/util.py
pypesto/version.py
pypesto/engine/__init__.py
pypesto/engine/base.py
pypesto/engine/mpi_pool.py
pypesto/engine/multi_process.py
pypesto/engine/multi_thread.py
pypesto/engine/single_core.py
pypesto/engine/task.py
pypesto/ensemble/__init__.py
pypesto/ensemble/covariance_analysis.py
pypesto/ensemble/dimension_reduction.py
pypesto/ensemble/ensemble.py
pypesto/ensemble/task.py
pypesto/ensemble/util.py
pypesto/hierarchical/__init__.py
pypesto/hierarchical/base_parameter.py
pypesto/hierarchical/base_problem.py
pypesto/hierarchical/base_solver.py
pypesto/hierarchical/inner_calculator_collector.py
pypesto/hierarchical/petab.py
pypesto/hierarchical/ordinal/__init__.py
pypesto/hierarchical/ordinal/calculator.py
pypesto/hierarchical/ordinal/parameter.py
pypesto/hierarchical/ordinal/problem.py
pypesto/hierarchical/ordinal/solver.py
pypesto/hierarchical/relative/__init__.py
pypesto/hierarchical/relative/calculator.py
pypesto/hierarchical/relative/parameter.py
pypesto/hierarchical/relative/problem.py
pypesto/hierarchical/relative/solver.py
pypesto/hierarchical/relative/util.py
pypesto/hierarchical/semiquantitative/__init__.py
pypesto/hierarchical/semiquantitative/calculator.py
pypesto/hierarchical/semiquantitative/parameter.py
pypesto/hierarchical/semiquantitative/problem.py
pypesto/hierarchical/semiquantitative/solver.py
pypesto/history/__init__.py
pypesto/history/amici.py
pypesto/history/base.py
pypesto/history/csv.py
pypesto/history/generate.py
pypesto/history/hdf5.py
pypesto/history/memory.py
pypesto/history/optimizer.py
pypesto/history/options.py
pypesto/history/util.py
pypesto/objective/__init__.py
pypesto/objective/aggregated.py
pypesto/objective/base.py
pypesto/objective/finite_difference.py
pypesto/objective/function.py
pypesto/objective/petab.py
pypesto/objective/pre_post_process.py
pypesto/objective/priors.py
pypesto/objective/amici/__init__.py
pypesto/objective/amici/amici.py
pypesto-0.5.8.dist-info/licenses/LICENSE
pypesto-0.5.8.dist-info/METADATA
pypesto-0.5.8.dist-info/WHEEL
pypesto-0.5.8.dist-info/top_level.txt
pypesto-0.5.8.dist-info/RECORD
